gann/__init__.py
gann/crossover.py
gann/gn_Cnn.py
gann/initparamobj.py
gann/makegene.py
gann/mutation.py
gann/runga.py
gann/saveparameters.py
gann/selection.py
gann-1.0.0.dist-info/METADATA
gann-1.0.0.dist-info/RECORD
gann-1.0.0.dist-info/WHEEL
gann-1.0.0.dist-info/top_level.txt
